pyucrio/__init__.py
pyucrio/_util.py
pyucrio/data/__init__.py
pyucrio/data/ucalgary/__init__.py
pyucrio/data/ucalgary/read/__init__.py
pyucrio/exceptions.py
pyucrio/pyucrio.py
pyucrio/tools/__init__.py
pyucrio/tools/_plot.py
pyucrio/tools/_util.py
pyucrio/tools/classes/__init__.py
pyucrio/tools/classes/site_map.py
pyucrio/tools/site_map/__init__.py
pyucrio/tools/site_map/_create_map.py
pyucrio-1.7.3.dist-info/METADATA
pyucrio-1.7.3.dist-info/WHEEL
pyucrio-1.7.3.dist-info/licenses/LICENSE
pyucrio-1.7.3.dist-info/RECORD
