Metadata-Version: 2.4
Name: pyucrio
Version: 1.7.3
Summary: Python library supporting data access and analysis for riometer instrument data
License: Apache-2.0
License-File: LICENSE
Keywords: space physics,space weather,riometer
Author: Darren Chaddock
Author-email: dchaddoc@ucalgary.ca
Maintainer: Darren Chaddock
Maintainer-email: dchaddoc@ucalgary.ca
Requires-Python: >=3.9
Classifier: Intended Audience :: Science/Research
Classifier: License :: OSI Approved :: Apache Software License
Classifier: Natural Language :: English
Classifier: Operating System :: MacOS :: MacOS X
Classifier: Operating System :: Microsoft :: Windows
Classifier: Operating System :: POSIX :: Linux
Classifier: Programming Language :: Python :: 3
Classifier: Programming Language :: Python :: 3.9
Classifier: Programming Language :: Python :: 3.10
Classifier: Programming Language :: Python :: 3.11
Classifier: Programming Language :: Python :: 3.12
Classifier: Programming Language :: Python :: 3.13
Classifier: Programming Language :: Python :: 3.14
Classifier: Topic :: Scientific/Engineering
Classifier: Topic :: Scientific/Engineering :: Physics
Classifier: Topic :: Software Development :: Libraries
Requires-Dist: aacgmv2 (>=2.6.2,<3.0.0)
Requires-Dist: cartopy (>=0.23.0,<0.24.0) ; python_version == "3.9"
Requires-Dist: cartopy (>=0.24.0,<0.25.0) ; python_version >= "3.10"
Requires-Dist: humanize (>=4.4.0,<5.0.0)
Requires-Dist: matplotlib (>=3.4.0,<4.0.0) ; python_version == "3.9"
Requires-Dist: matplotlib (>=3.5.0,<4.0.0) ; python_version >= "3.10"
Requires-Dist: numpy (>=1.21.0,<2.0.0) ; python_version == "3.9"
Requires-Dist: numpy (>=1.21.0,<2.3.0) ; python_version == "3.10"
Requires-Dist: numpy (>=1.21.0,<3.0.0) ; python_version >= "3.11"
Requires-Dist: pyproj (>=3.6.1,<4.0.0) ; python_version == "3.9"
Requires-Dist: pyproj (>=3.7.0,<4.0.0) ; python_version >= "3.10"
Requires-Dist: pyucalgarysrs (==1.24.0)
Requires-Dist: texttable (>=1.6.4,<2.0.0)
Project-URL: API Reference, https://docs-pyucrio.phys.ucalgary.ca
Project-URL: Homepage, https://github.com/ucalgary-srs/pyUCRio
Project-URL: Repository, https://github.com/ucalgary-srs/pyUCRio
Project-URL: UCalgary SRS Open Data Platform, https://data.phys.ucalgary.ca
